momsps/__init__.py
momsps/momsps.py
momsps/momsps_smooth.py
MomSPS-1.0.0.dist-info/LICENSE
MomSPS-1.0.0.dist-info/METADATA
MomSPS-1.0.0.dist-info/WHEEL
MomSPS-1.0.0.dist-info/top_level.txt
MomSPS-1.0.0.dist-info/RECORD
