Metadata-Version: 2.1
Name: MomSPS
Version: 1.0.0
Summary: Stochastic Polyak Step-sizes and Momentum: Convergence Guarantees and Practical Performance
Home-page: https://github.com/dimitris-oik/MomSPS
Author: Dimitris Oikonomou
Author-email: doikono1@jh.edu
License: UNKNOWN
Platform: UNKNOWN
Classifier: Programming Language :: Python :: 3
Classifier: License :: OSI Approved :: MIT License
Classifier: Operating System :: OS Independent
Requires-Python: >=3.8.0
License-File: LICENSE
Requires-Dist: numpy
Requires-Dist: torch
